gmail_attachment_downloader/__init__.py
gmail_attachment_downloader/__main__.py
gmail_attachment_downloader-0.0.2.dist-info/LICENSE
gmail_attachment_downloader-0.0.2.dist-info/METADATA
gmail_attachment_downloader-0.0.2.dist-info/WHEEL
gmail_attachment_downloader-0.0.2.dist-info/entry_points.txt
gmail_attachment_downloader-0.0.2.dist-info/top_level.txt
gmail_attachment_downloader-0.0.2.dist-info/RECORD
