Metadata-Version: 2.1
Name: gmail-attachment-downloader
Version: 0.0.2
Summary: A command line application that downloads all the gmail attachments with the specified format and search terms
Home-page: https://github.com/douglascdev/gmail_attachment_downloader
Author: Douglas
Author-email: douglasc.dev@gmail.com
License: MIT License
Keywords: email,gmail,attachment,download
Platform: UNKNOWN
Requires-Dist: click (==7.1.2)
Requires-Dist: IMAPClient (==2.2.0)
Requires-Dist: importlib-metadata (==3.10.0)
Requires-Dist: keyring (==23.0.1)
Requires-Dist: pywin32-ctypes (==0.2.0)
Requires-Dist: six (==1.15.0)
Requires-Dist: zipp (==3.4.1)
